matplotcheck/__init__.py
matplotcheck/autograde.py
matplotcheck/base.py
matplotcheck/cases.py
matplotcheck/folium.py
matplotcheck/notebook.py
matplotcheck/raster.py
matplotcheck/timeseries.py
matplotcheck/vector.py
matplotcheck-0.1.4.dist-info/LICENSE
matplotcheck-0.1.4.dist-info/METADATA
matplotcheck-0.1.4.dist-info/WHEEL
matplotcheck-0.1.4.dist-info/top_level.txt
matplotcheck-0.1.4.dist-info/RECORD
