Metadata-Version: 2.1
Name: matplotcheck
Version: 0.1.4
Summary: Functions to check Matplotlib plot outputs
Home-page: https://github.com/earthlab/matplotcheck
Maintainer: Leah Wasser
Maintainer-email: leah.wasser@colorado.edu
License: UNKNOWN
Platform: UNKNOWN
Classifier: Intended Audience :: Developers
Classifier: License :: OSI Approved :: BSD License
Classifier: Programming Language :: Python
Classifier: Topic :: Software Development
Classifier: Operating System :: Microsoft :: Windows
Classifier: Operating System :: POSIX
Classifier: Operating System :: Unix
Classifier: Operating System :: MacOS
Requires-Dist: numpy (>=1.14.0)
Requires-Dist: folium
Requires-Dist: geopandas
Requires-Dist: matplotlib (>=2.0.0)
Requires-Dist: rasterio
Requires-Dist: scipy
